[{"town":"\u5b9c\u862d\u5e02","village":"\u795e\u8fb2\u91cc","name":"\u8cf4\u6625\u65fa"},{"town":"\u5b9c\u862d\u5e02","village":"\u6c11\u6b0a\u91cc","name":"\u5c24\u69ae\u6dcb"},{"town":"\u5b9c\u862d\u5e02","village":"\u6c11\u751f\u91cc","name":"\u5f35\u4f51\u9621"},{"town":"\u5b9c\u862d\u5e02","village":"\u6607\u5e73\u91cc","name":"\u9ec3\u8302\u6797"},{"town":"\u5b9c\u862d\u5e02","village":"\u5927\u6771\u91cc","name":"\u4faf\u4f69\u5a77"},{"town":"\u5b9c\u862d\u5e02","village":"\u65b0\u8208\u91cc","name":"\u65b9\u7f8e\u73e0"},{"town":"\u5b9c\u862d\u5e02","village":"\u548c\u7766\u91cc","name":"\u9ec3\u6587\u9f8d"},{"town":"\u5b9c\u862d\u5e02","village":"\u9032\u58eb\u91cc","name":"\u9673\u6b63\u9054"},{"town":"\u5b9c\u862d\u5e02","village":"\u5357\u6a4b\u91cc","name":"\u6797\u6176\u96f2"},{"town":"\u5b9c\u862d\u5e02","village":"\u5efa\u696d\u91cc","name":"\u674e\u6c38"},{"town":"\u5b9c\u862d\u5e02","village":"\u5357\u6d25\u91cc","name":"\u6797\u8070\u660e"},{"town":"\u5b9c\u862d\u5e02","village":"\u51f1\u65cb\u91cc","name":"\u6797\u677e\u6c38"},{"town":"\u5b9c\u862d\u5e02","village":"\u9ece\u660e\u91cc","name":"\u6797\u6b63\u7fa9"},{"town":"\u5b9c\u862d\u5e02","village":"\u6771\u6751\u91cc","name":"\u6797\u5409\u96c4"},{"town":"\u5b9c\u862d\u5e02","village":"\u5ef6\u5e73\u91cc","name":"\u6797\u6c34\u84ee"},{"town":"\u5b9c\u862d\u5e02","village":"\u4e03\u5f35\u91cc","name":"\u6797\u5fe0\u52dd"},{"town":"\u5b9c\u862d\u5e02","village":"\u6148\u5b89\u91cc","name":"\u5468\u963f\u901a"},{"town":"\u5b9c\u862d\u5e02","village":"\u65b0\u6c11\u91cc","name":"\u5f35\u932b\u6607"},{"town":"\u5b9c\u862d\u5e02","village":"\u6771\u9580\u91cc","name":"\u674e\u8302\u5e9a"},{"town":"\u5b9c\u862d\u5e02","village":"\u4e2d\u6b63\u91cc","name":"\u90b1\u660e\u82b3"},{"town":"\u5b9c\u862d\u5e02","village":"\u5c0f\u6771\u91cc","name":"\u9ec3\u5efa\u6a39"},{"town":"\u5b9c\u862d\u5e02","village":"\u83dc\u5712\u91cc","name":"\u7c21\u8302\u9686"},{"town":"\u5b9c\u862d\u5e02","village":"\u5b5d\u5ec9\u91cc","name":"\u5433\u5065\u7fa9"},{"town":"\u5b9c\u862d\u5e02","village":"\u65b0\u751f\u91cc","name":"\u9ec3\u6b63\u96c4"},{"town":"\u5b9c\u862d\u5e02","village":"\u832d\u767d\u91cc","name":"\u6797\u6587\u96c4"},{"town":"\u5b9c\u862d\u5e02","village":"\u5317\u6d25\u91cc","name":"\u5433\u963f\u677e"},{"town":"\u5b9c\u862d\u5e02","village":"\u6885\u6d32\u91cc","name":"\u6797\u6c82\u68e3"},{"town":"\u5b9c\u862d\u5e02","village":"\u5317\u9580\u91cc","name":"\u7f85\u78a7\u6587"},{"town":"\u5b9c\u862d\u5e02","village":"\u6176\u548c\u91cc","name":"\u9673\u68df\u6a11"},{"town":"\u5b9c\u862d\u5e02","village":"\u9102\u738b\u91cc","name":"\u6797\u9298\u4fe1"},{"town":"\u5b9c\u862d\u5e02","village":"\u4e2d\u5c71\u91cc","name":"\u9ec3\u6b63\u6b21"},{"town":"\u5b9c\u862d\u5e02","village":"\u897f\u9580\u91cc","name":"\u90ed\u6c38\u5168"},{"town":"\u5b9c\u862d\u5e02","village":"\u5927\u9053\u91cc","name":"\u738b\u7d39\u9f8d"},{"town":"\u5b9c\u862d\u5e02","village":"\u5357\u9580\u91cc","name":"\u6797\u627f\u8521"},{"town":"\u5b9c\u862d\u5e02","village":"\u8ca0\u90ed\u91cc","name":"\u5289\u6b63\u7530"},{"town":"\u5b9c\u862d\u5e02","village":"\u6c11\u65cf\u91cc","name":"\u6e38\u6cf3\u6797"},{"town":"\u5b9c\u862d\u5e02","village":"\u5efa\u8ecd\u91cc","name":"\u6f58\u8302\u7533"},{"town":"\u5b9c\u862d\u5e02","village":"\u601d\u6e90\u91cc","name":"\u66fe\u5357\u570b"},{"town":"\u5b9c\u862d\u5e02","village":"\u6587\u5316\u91cc","name":"\u9673\u5fd7\u9d3b"},{"town":"\u5b9c\u862d\u5e02","village":"\u5fa9\u8208\u91cc","name":"\u8b1d\u74ca\u7389"},{"town":"\u7f85\u6771\u93ae","village":"\u5927\u65b0\u91cc","name":"\u9673\u69ae\u83ef"},{"town":"\u7f85\u6771\u93ae","village":"\u6771\u5b89\u91cc","name":"\u6797\u679d\u677e"},{"town":"\u7f85\u6771\u93ae","village":"\u65b0\u7fa4\u91cc","name":"\u6797\u9326\u6d0b"},{"town":"\u7f85\u6771\u93ae","village":"\u7f85\u838a\u91cc","name":"\u694a\u5ddd\u5bcc"},{"town":"\u7f85\u6771\u93ae","village":"\u5357\u660c\u91cc","name":"\u6797\u78a7\u971e"},{"town":"\u7f85\u6771\u93ae","village":"\u5357\u8c6a\u91cc","name":"\u9673\u69ae\u7f8e"},{"town":"\u7f85\u6771\u93ae","village":"\u6210\u529f\u91cc","name":"\u6797\u8070\u6587"},{"town":"\u7f85\u6771\u93ae","village":"\u4ec1\u5fb7\u91cc","name":"\u6797\u555f\u6771"},{"town":"\u7f85\u6771\u93ae","village":"\u6f22\u6c11\u91cc","name":"\u5ed6\u58eb\u8b00"},{"town":"\u7f85\u6771\u93ae","village":"\u897f\u5b89\u91cc","name":"\u6797\u5fe0\u6587"},{"town":"\u7f85\u6771\u93ae","village":"\u5317\u6210\u91cc","name":"\u9673\u5fe0\u5fd7"},{"town":"\u7f85\u6771\u93ae","village":"\u8ce2\u6587\u91cc","name":"\u6e38\u672c\u5168"},{"town":"\u7f85\u6771\u93ae","village":"\u516c\u6b63\u91cc","name":"\u6d2a\u671d\u8070"},{"town":"\u7f85\u6771\u93ae","village":"\u96c6\u7965\u91cc","name":"\u8b1d\u8302\u5ddd"},{"town":"\u7f85\u6771\u93ae","village":"\u4fe1\u7fa9\u91cc","name":"\u66fe\u9023\u679d"},{"town":"\u7f85\u6771\u93ae","village":"\u7af9\u6797\u91cc","name":"\u9ec3\u6c38\u548c"},{"town":"\u7f85\u6771\u93ae","village":"\u4ec1\u611b\u91cc","name":"\u90b1\u4e00\u5cf0"},{"town":"\u7f85\u6771\u93ae","village":"\u6a39\u6797\u91cc","name":"\u6797\u5fe0\u767c"},{"town":"\u7f85\u6771\u93ae","village":"\u570b\u83ef\u91cc","name":"\u5442\u60e0\u537f"},{"town":"\u7f85\u6771\u93ae","village":"\u7dad\u63da\u91cc","name":"\u6c5f\u6dfb\u5176"},{"town":"\u7f85\u6771\u93ae","village":"\u958b\u660e\u91cc","name":"\u838a\u6dfb\u9418"},{"town":"\u7f85\u6771\u93ae","village":"\u4e2d\u5c71\u91cc","name":"\u8a31\u6842\u90ce"},{"town":"\u7f85\u6771\u93ae","village":"\u4ec1\u548c\u91cc","name":"\u9673\u5733\u8302"},{"town":"\u8607\u6fb3\u93ae","village":"\u9f8d\u5fb7\u91cc","name":"\u5f35\u6587\u91d1"},{"town":"\u8607\u6fb3\u93ae","village":"\u9802\u5bee\u91cc","name":"\u6797\u745e\u82b3"},{"town":"\u8607\u6fb3\u93ae","village":"\u6c38\u69ae\u91cc","name":"\u9673\u4fe1\u592b"},{"town":"\u8607\u6fb3\u93ae","village":"\u5b58\u4ec1\u91cc","name":"\u856d\u963f\u6dfb"},{"town":"\u8607\u6fb3\u93ae","village":"\u6e2f\u908a\u91cc","name":"\u6797\u8302\u677e"},{"town":"\u8607\u6fb3\u93ae","village":"\u5cb3\u660e\u91cc","name":"\u6731\u8303\u6cc9"},{"town":"\u8607\u6fb3\u93ae","village":"\u9698\u4e01\u91cc","name":"\u5f35\u6b63\u69ae"},{"town":"\u8607\u6fb3\u93ae","village":"\u65b0\u57ce\u91cc","name":"\u9673\u6a39\u798f"},{"town":"\u8607\u6fb3\u93ae","village":"\u8056\u6e56\u91cc","name":"\u5289\u798f\u5143"},{"town":"\u8607\u6fb3\u93ae","village":"\u8607\u897f\u91cc","name":"\u694a\u5149\u83ef"},{"town":"\u8607\u6fb3\u93ae","village":"\u8607\u5317\u91cc","name":"\u9673\u6dfb\u742a"},{"town":"\u8607\u6fb3\u93ae","village":"\u8607\u5357\u91cc","name":"\u5433\u67cf\u797a"},{"town":"\u8607\u6fb3\u93ae","village":"\u8607\u6771\u91cc","name":"\u85cd\u851a\u82ac"},{"town":"\u8607\u6fb3\u93ae","village":"\u9577\u5b89\u91cc","name":"\u5f35\u69b4\u67f1"},{"town":"\u8607\u6fb3\u93ae","village":"\u6c38\u5149\u91cc","name":"\u5289\u91d1\u5fb7"},{"town":"\u8607\u6fb3\u93ae","village":"\u6c38\u6625\u91cc","name":"\u5f35\u76db\u570b"},{"town":"\u8607\u6fb3\u93ae","village":"\u6c38\u6a02\u91cc","name":"\u4fde\u5cb8\u8cd3"},{"town":"\u8607\u6fb3\u93ae","village":"\u5357\u5b89\u91cc","name":"\u6797\u91d1\u6e90"},{"town":"\u8607\u6fb3\u93ae","village":"\u5357\u6b63\u91cc","name":"\u6797\u654f\u5b8f"},{"town":"\u8607\u6fb3\u93ae","village":"\u5357\u6210\u91cc","name":"\u5f35\u8aa0\u70cb"},{"town":"\u8607\u6fb3\u93ae","village":"\u5357\u8208\u91cc","name":"\u9ec3\u91d1\u4f86"},{"town":"\u8607\u6fb3\u93ae","village":"\u5357\u5be7\u91cc","name":"\u694a\u5f69\u7df9"},{"town":"\u8607\u6fb3\u93ae","village":"\u5357\u5efa\u91cc","name":"\u5433\u91d1\u9f8d"},{"town":"\u8607\u6fb3\u93ae","village":"\u6771\u6fb3\u91cc","name":"\u9673\u5fb7\u7537"},{"town":"\u8607\u6fb3\u93ae","village":"\u5357\u5f37\u91cc","name":"\u9ec3\u5146\u76db"},{"town":"\u8607\u6fb3\u93ae","village":"\u671d\u967d\u91cc","name":"\u674e\u9806\u7fa9"},{"town":"\u982d\u57ce\u93ae","village":"\u77f3\u57ce\u91cc","name":"\u6c88\u5b89\u4ead"},{"town":"\u982d\u57ce\u93ae","village":"\u5927\u91cc\u91cc","name":"\u5c24\u6dfb\u4e01"},{"town":"\u982d\u57ce\u93ae","village":"\u5927\u6eaa\u91cc","name":"\u6c88\u745e\u96f2"},{"town":"\u982d\u57ce\u93ae","village":"\u5408\u8208\u91cc","name":"\u5f35\u6b63\u76ca"},{"town":"\u982d\u57ce\u93ae","village":"\u66f4\u65b0\u91cc","name":"\u9673\u7e7c\u932b"},{"town":"\u982d\u57ce\u93ae","village":"\u5916\u6fb3\u91cc","name":"\u77f3\u932b\u714c"},{"town":"\u982d\u57ce\u93ae","village":"\u6e2f\u53e3\u91cc","name":"\u674e\u9686\u5409"},{"town":"\u982d\u57ce\u93ae","village":"\u6b66\u71df\u91cc","name":"\u6e38\u570b\u6dfb"},{"town":"\u982d\u57ce\u93ae","village":"\u5927\u5751\u91cc","name":"\u9673\u932b\u83ef"},{"town":"\u982d\u57ce\u93ae","village":"\u57ce\u6771\u91cc","name":"\u6e38\u932b\u8ca1"},{"town":"\u982d\u57ce\u93ae","village":"\u57ce\u5317\u91cc","name":"\u674e\u6728\u9023"},{"town":"\u982d\u57ce\u93ae","village":"\u57ce\u897f\u91cc","name":"\u674e\u9577\u93ae"},{"town":"\u982d\u57ce\u93ae","village":"\u57ce\u5357\u91cc","name":"\u6797\u6625\u4e09"},{"town":"\u982d\u57ce\u93ae","village":"\u7af9\u5b89\u91cc","name":"\u9673\u68ee\u9298"},{"town":"\u982d\u57ce\u93ae","village":"\u65b0\u5efa\u91cc","name":"\u5289\u6e05\u5fb7"},{"town":"\u982d\u57ce\u93ae","village":"\u62d4\u96c5\u91cc","name":"\u9ec3\u6b63\u4f86"},{"town":"\u982d\u57ce\u93ae","village":"\u798f\u6210\u91cc","name":"\u9112\u69ae\u5bcc"},{"town":"\u982d\u57ce\u93ae","village":"\u91d1\u9762\u91cc","name":"\u5289\u69ae\u83ef"},{"town":"\u982d\u57ce\u93ae","village":"\u91d1\u76c8\u91cc","name":"\u6797\u6f22\u9f8d"},{"town":"\u982d\u57ce\u93ae","village":"\u9802\u57d4\u91cc","name":"\u90b1\u5bc5\u6b21"},{"town":"\u982d\u57ce\u93ae","village":"\u4e0b\u57d4\u91cc","name":"\u6797\u592a\u6e90"},{"town":"\u982d\u57ce\u93ae","village":"\u4e2d\u5d19\u91cc","name":"\u856d\u5efa\u660e"},{"town":"\u982d\u57ce\u93ae","village":"\u4e8c\u57ce\u91cc","name":"\u5f35\u91d1\u9023"},{"town":"\u982d\u57ce\u93ae","village":"\u9f9c\u5c71\u91cc","name":"\u7c21\u82f1\u4fca"},{"town":"\u7901\u6eaa\u9109","village":"\u767d\u96f2\u6751","name":"\u9678\u5929\u8cdc"},{"town":"\u7901\u6eaa\u9109","village":"\u7389\u77f3\u6751","name":"\u6e38\u677e\u68cb"},{"town":"\u7901\u6eaa\u9109","village":"\u5fb7\u967d\u6751","name":"\u6797\u5f18\u5805"},{"town":"\u7901\u6eaa\u9109","village":"\u5927\u5fe0\u6751","name":"\u85cd\u4e09\u90ce"},{"town":"\u7901\u6eaa\u9109","village":"\u5927\u7fa9\u6751","name":"\u6797\u7965\u50b3"},{"town":"\u7901\u6eaa\u9109","village":"\u516d\u7d50\u6751","name":"\u6797\u5982\u67f1"},{"town":"\u7901\u6eaa\u9109","village":"\u4e8c\u9f8d\u6751","name":"\u6797\u7fa9\u6210"},{"town":"\u7901\u6eaa\u9109","village":"\u6642\u6f6e\u6751","name":"\u984f\u7389\u6842"},{"town":"\u7901\u6eaa\u9109","village":"\u7389\u7530\u6751","name":"\u6e38\u65b0\u7210"},{"town":"\u7901\u6eaa\u9109","village":"\u4e09\u6c11\u6751","name":"\u6797\u963f\u9023"},{"town":"\u7901\u6eaa\u9109","village":"\u6797\u7f8e\u6751","name":"\u6e38\u6709\u5fb7"},{"town":"\u7901\u6eaa\u9109","village":"\u767d\u9d5d\u6751","name":"\u6e38\u58ec\u7678"},{"town":"\u7901\u6eaa\u9109","village":"\u7389\u5149\u6751","name":"\u838a\u6625\u571f"},{"town":"\u7901\u6eaa\u9109","village":"\u5149\u6b66\u6751","name":"\u6797\u6587\u9032"},{"town":"\u7901\u6eaa\u9109","village":"\u5433\u6c99\u6751","name":"\u8cf4\u589e\u7530"},{"town":"\u7901\u6eaa\u9109","village":"\u9f8d\u6f6d\u6751","name":"\u5433\u6587\u751f"},{"town":"\u7901\u6eaa\u9109","village":"\u530f\u5d19\u6751","name":"\u9ec3\u671d\u660e"},{"town":"\u7901\u6eaa\u9109","village":"\u4e8c\u7d50\u6751","name":"\u674e\u9298\u9054"},{"town":"\u58ef\u570d\u9109","village":"\u5409\u7965\u6751","name":"\u9673\u6728\u5764"},{"town":"\u58ef\u570d\u9109","village":"\u7f8e\u798f\u6751","name":"\u674e\u8302\u7537"},{"town":"\u58ef\u570d\u9109","village":"\u65b0\u5357\u6751","name":"\u6797\u79c0\u6200"},{"town":"\u58ef\u570d\u9109","village":"\u6771\u6e2f\u6751","name":"\u85cd\u6708\u6885"},{"town":"\u58ef\u570d\u9109","village":"\u5fa9\u8208\u6751","name":"\u738b\u5fb7\u5c71"},{"town":"\u58ef\u570d\u9109","village":"\u904e\u5dba\u6751","name":"\u90ed\u9032\u5fb7"},{"town":"\u58ef\u570d\u9109","village":"\u6c38\u93ae\u6751","name":"\u674e\u7167\u798f"},{"town":"\u58ef\u570d\u9109","village":"\u5fe0\u5b5d\u6751","name":"\u838a\u671d\u660e"},{"town":"\u58ef\u570d\u9109","village":"\u53e4\u4ead\u6751","name":"\u912d\u6587\u5c55"},{"town":"\u58ef\u570d\u9109","village":"\u529f\u52de\u6751","name":"\u6797\u9296\u751f"},{"town":"\u58ef\u570d\u9109","village":"\u7f8e\u57ce\u6751","name":"\u5433\u6a5c\u9054"},{"town":"\u58ef\u570d\u9109","village":"\u65b0\u793e\u6751","name":"\u5468\u6c76\u975a"},{"town":"\u58ef\u570d\u9109","village":"\u5927\u798f\u6751","name":"\u9673\u65b0\u6dfb"},{"town":"\u58ef\u570d\u9109","village":"\u53e4\u7d50\u6751","name":"\u8cf4\u5efa\u570b"},{"town":"\u54e1\u5c71\u9109","village":"\u54e1\u5c71\u6751","name":"\u694a\u69ae\u632f"},{"town":"\u54e1\u5c71\u9109","village":"\u5c1a\u5fb7\u6751","name":"\u6797\u671d\u57ce"},{"town":"\u54e1\u5c71\u9109","village":"\u60e0\u597d\u6751","name":"\u9ec3\u6c38\u4e7e"},{"town":"\u54e1\u5c71\u9109","village":"\u4e03\u8ce2\u6751","name":"\u9ad8\u660e\u82b3"},{"town":"\u54e1\u5c71\u9109","village":"\u6df1\u6e9d\u6751","name":"\u8b1d\u963f\u725b"},{"town":"\u54e1\u5c71\u9109","village":"\u84c1\u5df7\u6751","name":"\u9673\u6e05\u5168"},{"town":"\u54e1\u5c71\u9109","village":"\u5167\u57ce\u6751","name":"\u6731\u706b\u91d1"},{"town":"\u54e1\u5c71\u9109","village":"\u4e2d\u83ef\u6751","name":"\u5468\u6587\u79d1"},{"town":"\u54e1\u5c71\u9109","village":"\u6c38\u548c\u6751","name":"\u9673\u6eab\u826f"},{"town":"\u54e1\u5c71\u9109","village":"\u982d\u5206\u6751","name":"\u77f3\u7530\u4e2d"},{"town":"\u54e1\u5c71\u9109","village":"\u6795\u5c71\u6751","name":"\u674e\u671d\u6210"},{"town":"\u54e1\u5c71\u9109","village":"\u540c\u6a02\u6751","name":"\u6797\u99ff\u613f"},{"town":"\u54e1\u5c71\u9109","village":"\u6e56\u6771\u6751","name":"\u912d\u91d1\u91e7"},{"town":"\u54e1\u5c71\u9109","village":"\u9038\u4ed9\u6751","name":"\u6797\u6625\u714c"},{"town":"\u54e1\u5c71\u9109","village":"\u6e56\u5317\u6751","name":"\u674e\u6587\u6dfb"},{"town":"\u54e1\u5c71\u9109","village":"\u6e56\u897f\u6751","name":"\u5f35\u660e\u660c"},{"town":"\u51ac\u5c71\u9109","village":"\u6b66\u6df5\u6751","name":"\u6797\u6587\u6210"},{"town":"\u51ac\u5c71\u9109","village":"\u73cd\u73e0\u6751","name":"\u6797\u81ea\u5f37"},{"town":"\u51ac\u5c71\u9109","village":"\u88dc\u57ce\u6751","name":"\u9ec3\u5b89\u5e73"},{"town":"\u51ac\u5c71\u9109","village":"\u4e09\u5947\u6751","name":"\u674e\u6b63\u96c4"},{"town":"\u51ac\u5c71\u9109","village":"\u5927\u8208\u6751","name":"\u9673\u677e\u6839"},{"town":"\u51ac\u5c71\u9109","village":"\u6771\u57ce\u6751","name":"\u9ec3\u842c\u91d1"},{"town":"\u51ac\u5c71\u9109","village":"\u9999\u548c\u6751","name":"\u8a31\u6de5\u6d32"},{"town":"\u51ac\u5c71\u9109","village":"\u5357\u8208\u6751","name":"\u8cf4\u96f2\u5764"},{"town":"\u51ac\u5c71\u9109","village":"\u51ac\u5c71\u6751","name":"\u6797\u9326\u6d77"},{"town":"\u51ac\u5c71\u9109","village":"\u5b89\u5e73\u6751","name":"\u9673\u9577\u7fa9"},{"town":"\u51ac\u5c71\u9109","village":"\u592a\u548c\u6751","name":"\u6e38\u6e90\u5d07"},{"town":"\u51ac\u5c71\u9109","village":"\u516b\u5bf6\u6751","name":"\u8cf4\u6728\u679d"},{"town":"\u51ac\u5c71\u9109","village":"\u4e38\u5c71\u6751","name":"\u6e38\u535a\u826f"},{"town":"\u51ac\u5c71\u9109","village":"\u4e2d\u5c71\u6751","name":"\u674e\u632f\u798f"},{"town":"\u51ac\u5c71\u9109","village":"\u9806\u5b89\u6751","name":"\u6797\u6b63\u6b3d"},{"town":"\u51ac\u5c71\u9109","village":"\u6c38\u7f8e\u6751","name":"\u8a79\u7d20\u83ef"},{"town":"\u51ac\u5c71\u9109","village":"\u7fa4\u82f1\u6751","name":"\u5ed6\u653f\u570b"},{"town":"\u51ac\u5c71\u9109","village":"\u6e05\u6e9d\u6751","name":"\u6797\u8208\u5bb6"},{"town":"\u51ac\u5c71\u9109","village":"\u9e7f\u57d4\u6751","name":"\u6c5f\u84bc\u6587"},{"town":"\u51ac\u5c71\u9109","village":"\u5f97\u5b89\u6751","name":"\u9673\u4e16\u82f1"},{"town":"\u51ac\u5c71\u9109","village":"\u5ee3\u8208\u6751","name":"\u66fe\u70b3\u8302"},{"town":"\u51ac\u5c71\u9109","village":"\u5ee3\u5b89\u6751","name":"\u9ec3\u9806\u4f86"},{"town":"\u51ac\u5c71\u9109","village":"\u67ef\u6797\u6751","name":"\u9ec3\u6b63\u5b97"},{"town":"\u51ac\u5c71\u9109","village":"\u5927\u9032\u6751","name":"\u85cd\u7d30\u5ddd"},{"town":"\u4e94\u7d50\u9109","village":"\u4e09\u8208\u6751","name":"\u6c88\u798f\u52a9"},{"town":"\u4e94\u7d50\u9109","village":"\u4e8c\u7d50\u6751","name":"\u7c21\u6c5d\u80b2"},{"town":"\u4e94\u7d50\u9109","village":"\u93ae\u5b89\u6751","name":"\u5f35\u671d\u677e"},{"town":"\u4e94\u7d50\u9109","village":"\u4e0a\u56db\u6751","name":"\u7c21\u745e\u548c"},{"town":"\u4e94\u7d50\u9109","village":"\u4e2d\u8208\u6751","name":"\u674e\u78a7\u771f"},{"town":"\u4e94\u7d50\u9109","village":"\u56db\u7d50\u6751","name":"\u9673\u92d5\u6dee"},{"town":"\u4e94\u7d50\u9109","village":"\u798f\u8208\u6751","name":"\u5f35\u65b0\u83ef"},{"town":"\u4e94\u7d50\u9109","village":"\u4e94\u7d50\u6751","name":"\u9ec3\u6587\u5b8f"},{"town":"\u4e94\u7d50\u9109","village":"\u5927\u5409\u6751","name":"\u6797\u79c0\u82f1"},{"town":"\u4e94\u7d50\u9109","village":"\u5354\u548c\u6751","name":"\u9ec3\u9419\u5c71"},{"town":"\u4e94\u7d50\u9109","village":"\u5b5d\u5a01\u6751","name":"\u6797\u5733\u6e90"},{"town":"\u4e94\u7d50\u9109","village":"\u9326\u773e\u6751","name":"\u90b1\u653f\u5bcc"},{"town":"\u4e94\u7d50\u9109","village":"\u5229\u6fa4\u6751","name":"\u6797\u4f55\u826f"},{"town":"\u4e94\u7d50\u9109","village":"\u6210\u8208\u6751","name":"\u5f35\u91d1\u767c"},{"town":"\u4e94\u7d50\u9109","village":"\u5b63\u65b0\u6751","name":"\u6797\u708e\u5764"},{"town":"\u4e09\u661f\u9109","village":"\u54e1\u5c71\u6751","name":"\u5468\u6b63\u7fa9"},{"town":"\u4e09\u661f\u9109","village":"\u5929\u5c71\u6751","name":"\u912d\u7389\u5bc5"},{"town":"\u4e09\u661f\u9109","village":"\u5929\u798f\u6751","name":"\u5b8b\u9686\u6b3d"},{"town":"\u4e09\u661f\u9109","village":"\u96d9\u8ce2\u6751","name":"\u694a\u6b63\u96c4"},{"town":"\u4e09\u661f\u9109","village":"\u4eba\u548c\u6751","name":"\u5ed6\u7196"},{"town":"\u4e09\u661f\u9109","village":"\u7fa9\u5fb7\u6751","name":"\u66fe\u904b\u7389"},{"town":"\u4e09\u661f\u9109","village":"\u96c6\u6176\u6751","name":"\u5f6d\u6b63\u8ce2"},{"town":"\u4e09\u661f\u9109","village":"\u6708\u7709\u6751","name":"\u9673\u975c\u6ce2"},{"town":"\u4e09\u661f\u9109","village":"\u62f1\u7167\u6751","name":"\u912d\u963f\u8ca1"},{"town":"\u4e09\u661f\u9109","village":"\u5927\u96b1\u6751","name":"\u8303\u671f\u52db"},{"town":"\u4e09\u661f\u9109","village":"\u884c\u5065\u6751","name":"\u5433\u6e05\u6eaa"},{"town":"\u4e09\u661f\u9109","village":"\u842c\u5fb7\u6751","name":"\u9673\u9577\u68ee"},{"town":"\u4e09\u661f\u9109","village":"\u8cb4\u6797\u6751","name":"\u6797\u5b9a\u6771"},{"town":"\u4e09\u661f\u9109","village":"\u842c\u5bcc\u6751","name":"\u66f9\u76db\u666f"},{"town":"\u4e09\u661f\u9109","village":"\u5927\u7fa9\u6751","name":"\u912d\u5764\u5b97"},{"town":"\u4e09\u661f\u9109","village":"\u5c1a\u6b66\u6751","name":"\u9673\u6167\u7433"},{"town":"\u4e09\u661f\u9109","village":"\u5927\u6d32\u6751","name":"\u9673\u6f6e\u96c4"},{"town":"\u4e09\u661f\u9109","village":"\u5c3e\u5879\u6751","name":"\u5f35\u8d8a\u767b"},{"town":"\u5927\u540c\u9109","village":"\u5bd2\u6eaa\u6751","name":"\u80e1\u82b3\u69ae"},{"town":"\u5927\u540c\u9109","village":"\u5d19\u57e4\u6751","name":"\u5361\u6587\u7c73\u5167"},{"town":"\u5927\u540c\u9109","village":"\u677e\u7f85\u6751","name":"\u9127\u674e\u963f\u83ca"},{"town":"\u5927\u540c\u9109","village":"\u5fa9\u8208\u6751","name":"\u9673\u91d1\u65fa"},{"town":"\u5927\u540c\u9109","village":"\u82f1\u58eb\u6751","name":"\u5f35\u963f\u7389"},{"town":"\u5927\u540c\u9109","village":"\u6a02\u6c34\u6751","name":"\u7c21\u9032\u5857"},{"town":"\u5927\u540c\u9109","village":"\u592a\u5e73\u6751","name":"\u674e\u9298\u5b9c"},{"town":"\u5927\u540c\u9109","village":"\u56db\u5b63\u6751","name":"\u9ec3\u91d1\u6d77"},{"town":"\u5927\u540c\u9109","village":"\u5357\u5c71\u6751","name":"\u5442\u842c\u798f"},{"town":"\u5927\u540c\u9109","village":"\u8302\u5b89\u6751","name":"\u9673\u6709\u70ba"},{"town":"\u5357\u6fb3\u9109","village":"\u5357\u6fb3\u6751","name":"\u6797\u662d\u8f1d"},{"town":"\u5357\u6fb3\u9109","village":"\u78a7\u5019\u6751","name":"\u8607\u9748\u540e"},{"town":"\u5357\u6fb3\u9109","village":"\u6771\u5cb3\u6751","name":"\u8b1d\u660c\u570b"},{"town":"\u5357\u6fb3\u9109","village":"\u91d1\u5cb3\u6751","name":"\u674e\u5fe0\u4fe1"},{"town":"\u5357\u6fb3\u9109","village":"\u6b66\u5854\u6751","name":"\u6e38\u7d04\u7ff0"},{"town":"\u5357\u6fb3\u9109","village":"\u91d1\u6d0b\u6751","name":"\u8303\u5b88\u81e3"},{"town":"\u5357\u6fb3\u9109","village":"\u6fb3\u82b1\u6751","name":"\u5b54\u671d\u654f"}]